VLSI /ALU_SHL_5bit.v
module ALU_SHL_5bit (
    input wire [4:0] A, B,
    output reg [4:0] R,
    output reg CF
);

    wire [2:0] shift_amt;
    assign shift_amt = B[2:0]; // Use only 3 LSBs of B

    always @(*) begin
        case (shift_amt)
            3'd0: 
                begin
                    R = A;            // No shift
                    CF = 1'b0;
                end
            3'd1: 
                begin
                    R = A << 1;       // Shift left by 1
                    CF = A[4];
                end
            3'd2: 
                begin
                    R = A << 2;       // Shift left by 2
                    CF = A[3];
                end
            3'd3: 
                begin
                    R = A << 3;       // Shift left by 3
                    CF = A[2];
                end
            3'd4: 
                begin
                    R = A << 4;       // Shift left by 4
                    CF = A[1];
                end
            3'd5: 
                begin
                    R = A << 5;
                    CF = A[0];
                end                

            default: 
                begin
                    R = 5'b00000;  // For shift_amt > 4, output will become zero
                    CF = 1'b0;
                end

        endcase
    end

endmodule

VLSI/ALU_NOT_5bit.v
module ALU_NOT_5bit 
(
    input wire [4:0] A,  
    output wire [4:0] R    
);

    assign R= ~A;

endmodule

VLSI/ALU.v
module ALU
(
    input wire [4:0] A, B,                   
    input wire OP,    
    output reg [4:0] R,     
    output wire CF,
    output wire SF,
    output wire ZF           
);

    wire [4:0] R_NOT, R_SHL;
    wire R_CF;

    // Instantiate modules
    ALU_NOT_5bit NOT1 ( .A(A), .R(R_NOT));
    ALU_SHL_5bit SHL1 ( .A(A), .B(B), .R(R_SHL), .CF(R_CF));

    always @(*) 
    begin
        case (OP)
            1'b0: // NOT operation
                begin 
                    R = R_NOT; 
                end
            1'b1: // left Shift 
                begin 
                    R = R_SHL;
                end
            default: 
                begin
                    R = 5'b00000;  
                end
        endcase
    end

    assign CF = OP? R_CF :1'b0;
    assign SF = R[4];
    assign ZF = ~(R[4] | R[3] | R[2] | R[1] | R[0]);

endmodule

VLSI/ALU_tb.v
module ALU_tb;
    reg [4:0] A, B;       
    reg OP;          
    wire [4:0] R;          
    wire CF;
    wire SF;
    wire ZF;

    ALU uut (
        .A(A),
        .B(B),
        .OP(OP),
        .R(R),
        .CF(CF),
        .SF(SF),
        .ZF(ZF)
    );

    initial begin
        $dumpfile("alu_test.vcd");
        $dumpvars(0, ALU_tb);

        A = 5'b00000; B = 5'b00000; OP = 1'b0;//not
        #10;

        A = 5'b10101; OP = 1'b0;
        #10;

        A = 5'b11111; OP = 1'b0;
        #10;

        A = 5'b11101; B = 5'b00000; OP = 1'b1;//shl 0
        #10;

        A = 5'b11101; B = 5'b00001; OP = 1'b1;
        #10;

        A = 5'b10101; B = 5'b00010; OP = 1'b1;
        #10;

        A = 5'b11101; B = 5'b00011; OP = 1'b1;
        #10;

        A = 5'b01010; B = 5'b00000; OP = 1'b1;
        #10;

        A = 5'b01010; B = 5'b00100; OP = 1'b1;//<<4
        #10;

        A = 5'b01010; B = 5'b00101; OP = 1'b1; //shl << 5
        #10;

        $finish;
    end

    initial begin
        $monitor("Time=%0t A=%b B=%b OP=%b -> R=%b CF=%b ZF=%b SF=%b", $time, A, B, OP, R, CF, ZF, SF);
    end

endmodule

VLSI/alu_test.vcd
$date
	Mon Jun  9 02:28:20 2025
$end
$version
	Icarus Verilog
$end
$timescale
	1s
$end
$scope module ALU_tb $end
$var wire 1 ! ZF $end
$var wire 1 " SF $end
$var wire 5 # R [4:0] $end
$var wire 1 $ CF $end
$var reg 5 % A [4:0] $end
$var reg 5 & B [4:0] $end
$var reg 1 ' OP $end
$scope module uut $end
$var wire 5 ( A [4:0] $end
$var wire 5 ) B [4:0] $end
$var wire 1 ' OP $end
$var wire 1 ! ZF $end
$var wire 1 " SF $end
$var wire 5 * R_SHL [4:0] $end
$var wire 5 + R_NOT [4:0] $end
$var wire 1 , R_CF $end
$var wire 1 $ CF $end
$var reg 5 - R [4:0] $end
$scope module NOT1 $end
$var wire 5 . A [4:0] $end
$var wire 5 / R [4:0] $end
$upscope $end
$scope module SHL1 $end
$var wire 5 0 A [4:0] $end
$var wire 5 1 B [4:0] $end
$var wire 3 2 shift_amt [2:0] $end
$var reg 1 , CF $end
$var reg 5 3 R [4:0] $end
$upscope $end
$upscope $end
$upscope $end
$enddefinitions $end
$comment Show the parameter values. $end
$dumpall
$end
#0
$dumpvars
b0 3
b0 2
b0 1
b0 0
b11111 /
b0 .
b11111 -
0,
b11111 +
b0 *
b0 )
b0 (
0'
b0 &
b0 %
0$
b11111 #
1"
0!
$end
#10
0"
b1010 #
b1010 -
b1010 +
b1010 /
b10101 *
b10101 3
b10101 %
b10101 (
b10101 .
b10101 0
#20
1!
b0 #
b0 -
b0 +
b0 /
b11111 *
b11111 3
b11111 %
b11111 (
b11111 .
b11111 0
#30
0!
1"
b11101 #
b11101 -
b10 +
b10 /
b11101 *
b11101 3
1'
b11101 %
b11101 (
b11101 .
b11101 0
#40
1$
b11010 #
b11010 -
1,
b11010 *
b11010 3
b1 2
b1 &
b1 )
b1 1
#50
0$
1"
0,
b10100 #
b10100 -
b10 2
b1010 +
b1010 /
b10100 *
b10100 3
b10 &
b10 )
b10 1
b10101 %
b10101 (
b10101 .
b10101 0
#60
0"
b1000 #
b1000 -
b1000 *
b1000 3
1$
b11 2
b10 +
b10 /
1,
b11 &
b11 )
b11 1
b11101 %
b11101 (
b11101 .
b11101 0
#70
0"
0$
b1010 #
b1010 -
b0 2
b10101 +
b10101 /
0,
b1010 *
b1010 3
b0 &
b0 )
b0 1
b1010 %
b1010 (
b1010 .
b1010 0
#80
1!
1$
b0 #
b0 -
1,
b0 *
b0 3
b100 2
b100 &
b100 )
b100 1
#90
0$
0,
b101 2
b101 &
b101 )
b101 1
